{
  "sections": [
    {
      "type": "breadcrumbs",
      "enabled": true
    },
    {
      "type": "product-block",
      "enabled": true
    },
    {
      "type": "related-products",
      "title": "Você também pode gostar"
    },
    {
      "type": "recommended-products",
      "title": "Quem comprou este produto, também comprou:"
    },
    {
      "type": "product-description",
      "enabled": true
    },
    {
      "type": "product-specifications",
      "enabled": true
    },
    {
      "type": "custom-html",
      "html": "<h4>Quer receber receitas, dicas e promoções? Cadastre-se ;)</h4>\n  <!-- Estilos CSS personalizados para o formulário, se for usar seu estilo, pode apagar essa linha -->\n<link rel=\"stylesheet\" type=\"text/css\" href=\"https://novo.nitronews.com.br/assets/css/fomularios-html.css\">\n<form action=\"https://novo.nitronews.com.br/formularios/submit-form-HTML\" method=\"post\" target=\"_blank\" id=\"formIntegracaoHTML\">\n\t<label for=\"email\">E-mail: </label>\n \t<input type=\"email\" name=\"email%%E-mail\" id=\"email\" required>\n\t<label for=\"nome\">Nome: </label>\n \t<input type=\"text\" name=\"nome%%Nome\" id=\"nome\">\n\t<!-- Não apagar as linhas abaixo -->\n\t<input type=\"hidden\" name=\"chave[]\" value=\"Lj75\">\n\t<input type=\"hidden\" name=\"cliente\" value=\"Tia Sônia\">\n\t<input type=\"hidden\" name=\"urlretorno\" value=\"https://www.emporiotiasonia.com.br\">\n\t<input type=\"submit\" name=\"enviar\" value=\"eu quero\">\n</form>"
    }
  ]
}